agr_cognito_py/__init__.py
agr_cognito_py/cognito_auth.py
agr_cognito_py/cognito_permissions.py
agr_cognito_py/config.py
agr_cognito_py/dependencies.py
agr_cognito_py/py.typed
agr_cognito_py-0.1.0.dist-info/METADATA
agr_cognito_py-0.1.0.dist-info/WHEEL
agr_cognito_py-0.1.0.dist-info/licenses/LICENSE
agr_cognito_py-0.1.0.dist-info/RECORD
