Metadata-Version: 2.4
Name: agr-cognito-py
Version: 0.1.0
Summary: AWS Cognito JWT authentication library for FastAPI applications
Project-URL: Homepage, https://github.com/alliance-genome/agr_cognito_py
Project-URL: Documentation, https://github.com/alliance-genome/agr_cognito_py#readme
Project-URL: Repository, https://github.com/alliance-genome/agr_cognito_py.git
Project-URL: Issues, https://github.com/alliance-genome/agr_cognito_py/issues
Author: Alliance of Genome Resources
License-Expression: MIT
License-File: LICENSE
Keywords: agr,authentication,aws,cognito,fastapi,jwt
Classifier: Development Status :: 4 - Beta
Classifier: Framework :: FastAPI
Classifier: Intended Audience :: Developers
Classifier: License :: OSI Approved :: MIT License
Classifier: Operating System :: OS Independent
Classifier: Programming Language :: Python :: 3
Classifier: Programming Language :: Python :: 3.8
Classifier: Programming Language :: Python :: 3.9
Classifier: Programming Language :: Python :: 3.10
Classifier: Programming Language :: Python :: 3.11
Classifier: Programming Language :: Python :: 3.12
Classifier: Topic :: Internet :: WWW/HTTP :: HTTP Servers
Classifier: Topic :: Security
Requires-Python: >=3.8
Requires-Dist: fastapi>=0.100.0
Requires-Dist: pyjwt>=2.8.0
Requires-Dist: python-jose[cryptography]>=3.3.0
Requires-Dist: requests>=2.28.0
Provides-Extra: dev
Requires-Dist: httpx>=0.24.0; extra == 'dev'
Requires-Dist: mypy>=1.0.0; extra == 'dev'
Requires-Dist: pytest-asyncio>=0.21.0; extra == 'dev'
Requires-Dist: pytest-cov>=4.0.0; extra == 'dev'
Requires-Dist: pytest>=7.0.0; extra == 'dev'
Requires-Dist: ruff>=0.1.0; extra == 'dev'
Requires-Dist: types-requests>=2.28.0; extra == 'dev'
